humanize_gcode/__init__.py
humanize_gcode/humanize_gcode.py
humanize_gcode-0.0.6.data/scripts/hucode
humanize_gcode-0.0.6.dist-info/METADATA
humanize_gcode-0.0.6.dist-info/WHEEL
humanize_gcode-0.0.6.dist-info/top_level.txt
humanize_gcode-0.0.6.dist-info/RECORD
