Metadata-Version: 2.1
Name: humanize-gcode
Version: 0.0.6
Summary: Annotates GCode files with human readable descriptions of commands
Home-page: https://github.com/BarrensZeppelin/humanize-gcode
Author: Oskar Haarklou Veileborg
Author-email: ohv1020@hotmail.com
License: MIT
Classifier: Programming Language :: Python :: 3.6
Requires-Python: >=3.6
Requires-Dist: lxml[html_clean]
Requires-Dist: requests_html
Requires-Dist: crayons
Requires-Dist: appdirs
